mdl_density_histogram-1.1.4.dist-info/RECORD
mdl_density_histogram-1.1.4.dist-info/WHEEL
mdl_density_histogram-1.1.4.dist-info/top_level.txt
mdl_density_histogram-1.1.4.dist-info/METADATA
mdl_density_histogram-1.1.4.dist-info/licenses/LICENSE
mdl_density_hist/mdl_hist.cpython-314t-darwin.so
mdl_density_hist/__init__.py
mdl_density_hist/mdl_hist.pyx
