Metadata-Version: 2.4
Name: MDL-Density-Histogram
Version: 1.1.4
Summary: Cython-accelerated MDL histogram density estimation with dynamic programming, implementing Kontkanen & Myllymaki's algorithm (JMLR 2007).
Author-email: Götz Grimmer <goetz-dev@web.de>
Maintainer-email: Götz Grimmer <goetz-dev@web.de>
License: Apache-2.0
Project-URL: Repository, https://github.com/MrTarantoga/MDL-Density-Histogram
Requires-Python: >=3.11
License-File: LICENSE
Provides-Extra: tests
Requires-Dist: pytest; extra == "tests"
Requires-Dist: pytest-xdist; extra == "tests"
Requires-Dist: pandas; extra == "tests"
Requires-Dist: pyarrow; extra == "tests"
Requires-Dist: brotli; extra == "tests"
Dynamic: license-file
